merged_excel_tools/__init__.py
merged_excel_tools-1.4.dist-info/METADATA
merged_excel_tools-1.4.dist-info/RECORD
merged_excel_tools-1.4.dist-info/WHEEL
merged_excel_tools-1.4.dist-info/top_level.txt
