Metadata-Version: 2.1
Name: merged-excel-tools
Version: 1.4
Summary: merged cells excel tools
Home-page: https://github.com/zhangtao103239/read_merged_tools
Author: zhangtao103239
Author-email: zhangtao103239@163.com
License: UNKNOWN
Platform: UNKNOWN
Classifier: Programming Language :: Python :: 3
Classifier: License :: OSI Approved :: MIT License
Classifier: Operating System :: OS Independent
Requires-Dist: openpyxl
